odoo/addons/l10n_ro_partner_create_by_vat/README.rst
odoo/addons/l10n_ro_partner_create_by_vat/__init__.py
odoo/addons/l10n_ro_partner_create_by_vat/__manifest__.py
odoo/addons/l10n_ro_partner_create_by_vat/i18n/l10n_ro_partner_create_by_vat.pot
odoo/addons/l10n_ro_partner_create_by_vat/i18n/ro.po
odoo/addons/l10n_ro_partner_create_by_vat/migrations/14.0.2.3.1/pre-migration.py
odoo/addons/l10n_ro_partner_create_by_vat/models/__init__.py
odoo/addons/l10n_ro_partner_create_by_vat/models/res_partner.py
odoo/addons/l10n_ro_partner_create_by_vat/models/res_partner_anaf_scptva.py
odoo/addons/l10n_ro_partner_create_by_vat/models/res_partner_anaf_status.py
odoo/addons/l10n_ro_partner_create_by_vat/readme/CONTRIBUTORS.rst
odoo/addons/l10n_ro_partner_create_by_vat/readme/DESCRIPTION.rst
odoo/addons/l10n_ro_partner_create_by_vat/readme/INSTALL.rst
odoo/addons/l10n_ro_partner_create_by_vat/readme/USAGE.rst
odoo/addons/l10n_ro_partner_create_by_vat/security/ir.model.access.csv
odoo/addons/l10n_ro_partner_create_by_vat/static/description/icon.png
odoo/addons/l10n_ro_partner_create_by_vat/static/description/index.html
odoo/addons/l10n_ro_partner_create_by_vat/tests/__init__.py
odoo/addons/l10n_ro_partner_create_by_vat/tests/anaf_data.json
odoo/addons/l10n_ro_partner_create_by_vat/tests/test_create_partner_by_vat.py
odoo/addons/l10n_ro_partner_create_by_vat/views/partner_view.xml
odoo14_addon_l10n_ro_partner_create_by_vat-14.0.4.9.0.dist-info/METADATA
odoo14_addon_l10n_ro_partner_create_by_vat-14.0.4.9.0.dist-info/WHEEL
odoo14_addon_l10n_ro_partner_create_by_vat-14.0.4.9.0.dist-info/top_level.txt
odoo14_addon_l10n_ro_partner_create_by_vat-14.0.4.9.0.dist-info/RECORD
